epanet.cp311-win_amd64.pyd
docs/conf.py
epanet-msx-src/dispersion.h
epanet-msx-src/hash.c
epanet-msx-src/hash.h
epanet-msx-src/mathexpr.c
epanet-msx-src/mathexpr.h
epanet-msx-src/mempool.c
epanet-msx-src/mempool.h
epanet-msx-src/msxchem.c
epanet-msx-src/msxcompiler.c
epanet-msx-src/msxdict.h
epanet-msx-src/msxdispersion.c
epanet-msx-src/msxerr.c
epanet-msx-src/msxfile.c
epanet-msx-src/msxfuncs.c
epanet-msx-src/msxfuncs.h
epanet-msx-src/msxinp.c
epanet-msx-src/msxout.c
epanet-msx-src/msxproj.c
epanet-msx-src/msxqual.c
epanet-msx-src/msxrpt.c
epanet-msx-src/msxtank.c
epanet-msx-src/msxtoolkit.c
epanet-msx-src/msxtypes.h
epanet-msx-src/msxutils.c
epanet-msx-src/msxutils.h
epanet-msx-src/newton.c
epanet-msx-src/newton.h
epanet-msx-src/rk5.c
epanet-msx-src/rk5.h
epanet-msx-src/ros2.c
epanet-msx-src/ros2.h
epanet-msx-src/smatrix.c
epanet-msx-src/smatrix.h
epanet-msx-src/include/epanetmsx.h
epanet-msx-src/include/epanetmsx_export.h
epanet-src/AUTHORS
epanet-src/LICENSE
epanet-src/enumstxt.h
epanet-src/epanet.c
epanet-src/epanet2.c
epanet-src/epanet2.def
epanet-src/errors.dat
epanet-src/flowbalance.c
epanet-src/funcs.h
epanet-src/genmmd.c
epanet-src/hash.c
epanet-src/hash.h
epanet-src/hydcoeffs.c
epanet-src/hydraul.c
epanet-src/hydsolver.c
epanet-src/hydstatus.c
epanet-src/inpfile.c
epanet-src/input1.c
epanet-src/input2.c
epanet-src/input3.c
epanet-src/leakage.c
epanet-src/mempool.c
epanet-src/mempool.h
epanet-src/output.c
epanet-src/project.c
epanet-src/quality.c
epanet-src/qualreact.c
epanet-src/qualroute.c
epanet-src/report.c
epanet-src/rules.c
epanet-src/smatrix.c
epanet-src/text.h
epanet-src/types.h
epanet-src/validate.c
epanet-src/include/epanet2.h
epanet-src/include/epanet2_2.h
epanet-src/include/epanet2_enums.h
epanet-src/util/cstr_helper.c
epanet-src/util/cstr_helper.h
epanet-src/util/errormanager.c
epanet-src/util/errormanager.h
epanet-src/util/filemanager.c
epanet-src/util/filemanager.h
epanet_plus/VERSION
epanet_plus/__init__.py
epanet_plus/epanet_plus.c
epanet_plus-0.2.0.dist-info/licenses/LICENSE
epanet_plus-0.2.0.dist-info/METADATA
epanet_plus-0.2.0.dist-info/WHEEL
epanet_plus-0.2.0.dist-info/top_level.txt
epanet_plus-0.2.0.dist-info/RECORD
