Metadata-Version: 2.4
Name: epanet-plus
Version: 0.2.0
Summary: Python interface for EPANET-PLUS (incl. EPANET and EPANET-MSX)
Author-email: André Artelt <aartelt@techfak.uni-bielefeld.de>
License-Expression: MIT
Project-URL: Homepage, https://github.com/WaterFutures/EPANET-PLUS
Project-URL: Documentation, https://epanet-plus.readthedocs.io/en/stable/
Project-URL: Repository, https://github.com/WaterFutures/EPANET-PLUS.git
Project-URL: Issues, https://github.com/WaterFutures/EPANET-PLUS/issues
Keywords: epanet,water,networks,hydraulics,quality,simulations
Classifier: Development Status :: 4 - Beta
Classifier: Intended Audience :: Science/Research
Classifier: Programming Language :: Python :: 3
Classifier: Programming Language :: Python :: 3.10
Classifier: Programming Language :: Python :: 3.11
Classifier: Programming Language :: Python :: 3.12
Classifier: Programming Language :: Python :: 3.13
Classifier: Programming Language :: Python :: 3.14
Requires-Python: >=3.10
License-File: LICENSE
Dynamic: license-file
